acct/conf.py
acct/scripts.py
acct/version.py
acct/acct/init.py
acct/acct/backend/init.py
acct/acct/backend/contracts/init.py
acct/acct/contracts/init.py
acct/acct/metadata/init.py
acct/acct/metadata/contracts/init.py
acct/crypto/aesgcm256.py
acct/crypto/fernet.py
acct/crypto/init.py
acct/crypto/contracts/init.py
acct-8.6.2.dist-info/LICENSE
acct-8.6.2.dist-info/METADATA
acct-8.6.2.dist-info/WHEEL
acct-8.6.2.dist-info/entry_points.txt
acct-8.6.2.dist-info/top_level.txt
acct-8.6.2.dist-info/RECORD
