Metadata-Version: 2.1
Name: acct
Version: 8.6.2
Summary: Simple, secure, account and credential management
Home-page: https://saltstack.com
Author: Thomas S Hatch
Author-email: thatch@saltstack.com
Classifier: Operating System :: OS Independent
Classifier: Programming Language :: Python
Classifier: Programming Language :: Python :: 3.8
Classifier: Programming Language :: Python :: 3.9
Classifier: Programming Language :: Python :: 3.10
Classifier: Programming Language :: Python :: 3.11
Classifier: Development Status :: 5 - Production/Stable
Requires-Python: >=3.6
License-File: LICENSE
Requires-Dist: aiofiles
Requires-Dist: cryptography
Requires-Dist: dict-toolbox >=2.1.2
Requires-Dist: pop >=20
Requires-Dist: pop-config <13.0.0,>=9.0.0
Requires-Dist: pop-serial >=1.0.0
Requires-Dist: pyyaml >=6.0.1
Requires-Dist: rend >=6.3.1
